remoteconfig/__init__.py
remoteconfig/manager.py
remoteconfig/utils.py
remoteconfig-1.0.2.dist-info/METADATA
remoteconfig-1.0.2.dist-info/RECORD
remoteconfig-1.0.2.dist-info/WHEEL
remoteconfig-1.0.2.dist-info/top_level.txt
