Metadata-Version: 2.1
Name: remoteconfig
Version: 1.0.2
Summary: A simple wrapper for localconfig that allows for reading config from a remote server
Home-page: https://github.com/maxzheng/remoteconfig
Author: Max Zheng
Author-email: maxzheng.os @t gmail.com
License: MIT
Keywords: configuration remote http config
Platform: UNKNOWN
Classifier: Development Status :: 5 - Production/Stable
Classifier: Intended Audience :: Developers
Classifier: Topic :: Software Development
Classifier: License :: OSI Approved :: MIT License
Classifier: Programming Language :: Python :: 2
Classifier: Programming Language :: Python :: 2.6
Classifier: Programming Language :: Python :: 2.7
Requires-Dist: localconfig (>=1.0)
Requires-Dist: requests
